{
  "title": "Двуручный меч гитьянки",
  "resolved_title": "Двуручный меч гитьянки",
  "revision_found": true,
  "parse_found": true,
  "revision_timestamp": "2024-02-04T20:16:10Z",
  "wikitext_chars_query": 1990,
  "wikitext_chars_parse": 1990,
  "html_chars": 193700,
  "section_count": 6,
  "sections": [
    {
      "index": "1",
      "line": "Свойства"
    },
    {
      "index": "2",
      "line": "Урон"
    },
    {
      "index": "3",
      "line": "Особое"
    },
    {
      "index": "4",
      "line": "Действия с оружием"
    },
    {
      "index": "5",
      "line": "Получение"
    },
    {
      "index": "6",
      "line": "Навигация"
    }
  ]
}